xtendr/__init__.py
xtendr/xtendrbase.py
xtendr/xtendrsystem.py
xtendr-0.3.3.1.dist-info/licenses/LICENSE
xtendr-0.3.3.1.dist-info/METADATA
xtendr-0.3.3.1.dist-info/WHEEL
xtendr-0.3.3.1.dist-info/top_level.txt
xtendr-0.3.3.1.dist-info/RECORD
