Metadata-Version: 2.4
Name: XtendR
Version: 0.3.3.1
Summary: A modular plugin system for Python.
Home-page: https://www.gitea.com/Lerking/XtendR
Author: Jan Lerking
Author-email: 
Classifier: Programming Language :: Python :: 3.11
Classifier: License :: OSI Approved :: MIT License
Classifier: Operating System :: OS Independent
Requires-Python: >=3.11
License-File: LICENSE
Dynamic: author
Dynamic: classifier
Dynamic: description
Dynamic: description-content-type
Dynamic: home-page
Dynamic: license-file
Dynamic: requires-python
Dynamic: summary
